NetStructer/__init__.py
NetStructer/const.py
NetStrcuter-0.4.dist-info/LICENSE.txt
NetStrcuter-0.4.dist-info/METADATA
NetStrcuter-0.4.dist-info/WHEEL
NetStrcuter-0.4.dist-info/top_level.txt
NetStrcuter-0.4.dist-info/RECORD
