Metadata-Version: 2.1
Name: NetStrcuter
Version: 0.4
Summary: Simple library from low level socket api
Author: Haytam-Zakaria
Classifier: Programming Language :: Python :: 3
Classifier: Operating System :: OS Independent
Classifier: License :: OSI Approved :: MIT License
License-File: LICENSE.txt
